{
  "main": {
    "id": "f06272d1a8f1c5a1",
    "type": "split",
    "children": [
      {
        "id": "373c7d2c658d4242",
        "type": "tabs",
        "children": [
          {
            "id": "e7b3751439aea23f",
            "type": "leaf",
            "state": {
              "type": "markdown",
              "state": {
                "file": "IDEA_NOTE/CRAWLING/IDEA/크롤링 방식 변경_02.md",
                "mode": "source",
                "source": false
              }
            }
          },
          {
            "id": "002b54241d8d4772",
            "type": "leaf",
            "state": {
              "type": "markdown",
              "state": {
                "file": "IDEA_NOTE/CRAWLING/SCRUM/scrum_08.md",
                "mode": "source",
                "source": false
              }
            }
          },
          {
            "id": "df8a061450160283",
            "type": "leaf",
            "state": {
              "type": "image",
              "state": {
                "file": "IDEA_NOTE/자료/Pasted image 20231026134938.png"
              }
            }
          },
          {
            "id": "3f7d06c090def7af",
            "type": "leaf",
            "state": {
              "type": "image",
              "state": {
                "file": "IDEA_NOTE/자료/Pasted image 20231026135015.png"
              }
            }
          },
          {
            "id": "8f8b31342fa8aa9e",
            "type": "leaf",
            "state": {
              "type": "image",
              "state": {
                "file": "IDEA_NOTE/자료/Pasted image 20231026134938.png"
              }
            }
          }
        ],
        "currentTab": 1
      }
    ],
    "direction": "vertical"
  },
  "left": {
    "id": "d47c1a9d9402ddcd",
    "type": "split",
    "children": [
      {
        "id": "481e8c0072bd72fc",
        "type": "tabs",
        "children": [
          {
            "id": "73c958199096b504",
            "type": "leaf",
            "state": {
              "type": "file-explorer",
              "state": {
                "sortOrder": "alphabetical"
              }
            }
          },
          {
            "id": "766118ddc1ce17c5",
            "type": "leaf",
            "state": {
              "type": "search",
              "state": {
                "query": "tag:#idea02_크롤링",
                "matchingCase": false,
                "explainSearch": false,
                "collapseAll": false,
                "extraContext": false,
                "sortOrder": "alphabetical"
              }
            }
          },
          {
            "id": "301f258a90fd07b3",
            "type": "leaf",
            "state": {
              "type": "bookmarks",
              "state": {}
            }
          }
        ]
      }
    ],
    "direction": "horizontal",
    "width": 305.5
  },
  "right": {
    "id": "7b5ea5a8f67a403b",
    "type": "split",
    "children": [
      {
        "id": "bfbde6ea7ecb10d7",
        "type": "tabs",
        "children": [
          {
            "id": "b231fe74aaeb4000",
            "type": "leaf",
            "state": {
              "type": "backlink",
              "state": {
                "file": "IDEA_NOTE/CRAWLING/SCRUM/scrum_08.md",
                "collapseAll": false,
                "extraContext": false,
                "sortOrder": "alphabetical",
                "showSearch": false,
                "searchQuery": "",
                "backlinkCollapsed": false,
                "unlinkedCollapsed": true
              }
            }
          },
          {
            "id": "b0bb144192f3f3f0",
            "type": "leaf",
            "state": {
              "type": "outgoing-link",
              "state": {
                "file": "IDEA_NOTE/CRAWLING/SCRUM/scrum_08.md",
                "linksCollapsed": false,
                "unlinkedCollapsed": false
              }
            }
          },
          {
            "id": "eb65f6eeb5f9e094",
            "type": "leaf",
            "state": {
              "type": "tag",
              "state": {
                "sortOrder": "frequency",
                "useHierarchy": true
              }
            }
          },
          {
            "id": "392c0333866d4a69",
            "type": "leaf",
            "state": {
              "type": "outline",
              "state": {
                "file": "IDEA_NOTE/CRAWLING/SCRUM/scrum_08.md"
              }
            }
          },
          {
            "id": "4183a5da931f61b9",
            "type": "leaf",
            "state": {
              "type": "advanced-tables-toolbar",
              "state": {}
            }
          }
        ],
        "currentTab": 4
      }
    ],
    "direction": "horizontal",
    "width": 300
  },
  "left-ribbon": {
    "hiddenItems": {
      "switcher:Open quick switcher": false,
      "graph:Open graph view": false,
      "canvas:Create new canvas": false,
      "daily-notes:Open today's daily note": false,
      "templates:Insert template": false,
      "command-palette:Open command palette": false,
      "obsidian42-brat:BRAT": false,
      "obsidian-full-calendar:Open Full Calendar": false,
      "mermaid-tools:Open Mermaid Toolbar": false,
      "obsidian-excalidraw-plugin:Create new drawing": false,
      "table-editor-obsidian:Advanced Tables Toolbar": false
    }
  },
  "active": "002b54241d8d4772",
  "lastOpenFiles": [
    "IDEA_NOTE/자료/Pasted image 20231013142101.png",
    "IDEA_NOTE/자료/Pasted image 20231013141930.png",
    "IDEA_NOTE/STUDY/002_MARKDOWN.md",
    "IDEA_NOTE/CRAWLING/SCRUM/scrum_08.md",
    "IDEA_NOTE/CRAWLING/SCRUM/scrum_07.md",
    "IDEA_NOTE/CRAWLING/MANAGER.md",
    "IDEA_NOTE/CRAWLING/SCRUM/scrum_01.md",
    "IDEA_NOTE/PROJECT/SIDE/01_P_CRAWLER/01. 프로젝트 구성.md",
    "IDEA_NOTE/CRAWLING/IDEA/크롤링 방식 변경_01.md",
    "IDEA_NOTE/CRAWLING/IDEA/크롤링 방식 변경_02.md",
    "idea01_크롤링 방식 변경.md",
    "IDEA_NOTE/Excalidraw/Drawing 2023-10-17 04.26.21.excalidraw.md",
    "IDEA_NOTE/Excalidraw/Drawing 2023-09-25 00.24.23.excalidraw.md",
    "IDEA_NOTE/Excalidraw/Drawing 2023-09-28 18.16.27.excalidraw.md",
    "IDEA_NOTE/CRAWLING/IDEA/IDEA001_크롤링 개선 아이디어.md",
    "IDEA_NOTE/CRAWLING/COLLEAGUE/변재우.md",
    "IDEA_NOTE/CRAWLING/COLLEAGUE/노우정.md",
    "IDEA_NOTE/자료/Pasted Image 20230925002753_813.jpg",
    "IDEA_NOTE/자료/Pasted image 20231026134938.png",
    "IDEA_NOTE/자료/Pasted image 20231026135015.png",
    "Excalidraw/Drawing 2023-10-19 17.50.18.excalidraw.md",
    "IDEA_NOTE/TODO/1019목.md",
    "IDEA_NOTE/TODO/20231018.수.md",
    "IDEA_NOTE/TODO/Untitled.md",
    "IDEA_NOTE/CRAWLING/SCRUM/scrum_06.md",
    "IDEA_NOTE/STUDY/004_PROGRAMMERS.md",
    "IDEA_NOTE/STUDY/001_OBSIDIAN.md",
    "IDEA_NOTE/STUDY/003_GIT.md",
    "IDEA_NOTE/PRIVATE/팀 회의 준비.md",
    "IDEA_NOTE/PROJECT/SIDE/01_P_CRAWLER/02. ASIS.md",
    "Excalidraw",
    "IDEA_NOTE/PROJECT/SIDE/01_P_CRAWLER/자료/Pasted image 20231018111313.png",
    "TEST_OBSIDIAN",
    "IDEA_NOTE/PROJECT/SIDE/03_DJANGO",
    "IDEA_NOTE/PROJECT/SIDE/02_PLAYWRIGHT",
    "IDEA_NOTE/PROJECT/SIDE/01_P_CRAWLER/자료",
    "IDEA_NOTE/PROJECT/SIDE/01_P_CRAWLER",
    "IDEA_NOTE/PROJECT/SIDE",
    "IDEA_NOTE/PROJECT",
    "IDEA_NOTE/PRIVATE",
    "IDEA_NOTE/PRIVATE/Pasted image 20231013141930.png",
    "IDEA_NOTE/PRIVATE/Pasted image 20231013142101.png",
    "IDEA_NOTE/무제 파일.canvas",
    "IDEA_NOTE/CRAWLING/COLLEAGUE",
    "IDEA_NOTE/자료/Pasted Image 20231006082049_567.png",
    "Untitled 2.canvas",
    "IDEA_NOTE/자료/Pasted image 20230926151531.png",
    "Untitled 1.canvas",
    "Untitled.canvas",
    "IDEA_NOTE/자료/Pasted image 20230926151540.png"
  ]
}